statblk.py
statblk-1.37.dist-info/METADATA
statblk-1.37.dist-info/WHEEL
statblk-1.37.dist-info/entry_points.txt
statblk-1.37.dist-info/top_level.txt
statblk-1.37.dist-info/RECORD
