Metadata-Version: 2.4
Name: statblk
Version: 1.37
Summary: Gather essential disk and partition info for block devices and print it in a nice table
Home-page: https://github.com/yufei-pan/statblk
Author: Yufei Pan
Author-email: pan@zopyr.us
License: GPLv3+
Classifier: Programming Language :: Python :: 3
Classifier: Operating System :: POSIX :: Linux
Requires-Python: >=3.6
Requires-Dist: multiCMD>=1.35
Dynamic: author
Dynamic: author-email
Dynamic: classifier
Dynamic: description
Dynamic: description-content-type
Dynamic: home-page
Dynamic: license
Dynamic: requires-dist
Dynamic: requires-python
Dynamic: summary
